{
  "level_metadata": {
    "id": "lvl_19",
    "difficulty": 7,
    "seed": 204592165,
    "steps_to_solve": 50,
    "generator": {
      "wave": 2,
      "wave_label": "wave2_fragile",
      "slot_in_set": 9,
      "slot_global": 19,
      "base_seed": 4747,
      "mechanics": {
        "fragile": true,
        "crumbling": false,
        "moving": false,
        "portal": false
      }
    }
  },
  "world_settings": {
    "environment": "abyss_default",
    "gravity": 1
  },
  "start_state": {
    "pos": {
      "x": -6,
      "z": 14
    },
    "orientation": "vertical"
  },
  "hole_pos": {
    "x": 0,
    "z": 0
  },
  "tiles": [
    {
      "x": -6,
      "z": 14,
      "type": "normal"
    },
    {
      "x": -6,
      "z": 12,
      "type": "normal"
    },
    {
      "x": -6,
      "z": 13,
      "type": "normal"
    },
    {
      "x": -6,
      "z": 11,
      "type": "normal"
    },
    {
      "x": -5,
      "z": 11,
      "type": "normal"
    },
    {
      "x": -4,
      "z": 11,
      "type": "normal"
    },
    {
      "x": -5,
      "z": 10,
      "type": "normal"
    },
    {
      "x": -4,
      "z": 10,
      "type": "normal"
    },
    {
      "x": -3,
      "z": 10,
      "type": "normal"
    },
    {
      "x": -2,
      "z": 10,
      "type": "fragile"
    },
    {
      "x": -1,
      "z": 10,
      "type": "normal"
    },
    {
      "x": -2,
      "z": 11,
      "type": "normal"
    },
    {
      "x": -1,
      "z": 11,
      "type": "fragile"
    },
    {
      "x": -2,
      "z": 12,
      "type": "normal"
    },
    {
      "x": -1,
      "z": 12,
      "type": "normal"
    },
    {
      "x": -3,
      "z": 12,
      "type": "normal"
    },
    {
      "x": -3,
      "z": 11,
      "type": "normal"
    },
    {
      "x": -4,
      "z": 12,
      "type": "normal"
    },
    {
      "x": -1,
      "z": 13,
      "type": "normal"
    },
    {
      "x": -3,
      "z": 13,
      "type": "normal"
    },
    {
      "x": -2,
      "z": 13,
      "type": "normal"
    },
    {
      "x": -4,
      "z": 13,
      "type": "normal"
    },
    {
      "x": -4,
      "z": 14,
      "type": "normal"
    },
    {
      "x": -4,
      "z": 15,
      "type": "fragile"
    },
    {
      "x": -3,
      "z": 14,
      "type": "normal"
    },
    {
      "x": -3,
      "z": 15,
      "type": "normal"
    },
    {
      "x": -6,
      "z": 10,
      "type": "normal"
    },
    {
      "x": -6,
      "z": 9,
      "type": "fragile"
    },
    {
      "x": -5,
      "z": 9,
      "type": "fragile"
    },
    {
      "x": -6,
      "z": 8,
      "type": "normal"
    },
    {
      "x": -5,
      "z": 8,
      "type": "fragile"
    },
    {
      "x": -4,
      "z": 8,
      "type": "normal"
    },
    {
      "x": -4,
      "z": 9,
      "type": "normal"
    },
    {
      "x": -3,
      "z": 9,
      "type": "normal"
    },
    {
      "x": -2,
      "z": 14,
      "type": "normal"
    },
    {
      "x": -1,
      "z": 14,
      "type": "normal"
    },
    {
      "x": 0,
      "z": 13,
      "type": "normal"
    },
    {
      "x": 0,
      "z": 11,
      "type": "fragile"
    },
    {
      "x": 0,
      "z": 12,
      "type": "normal"
    },
    {
      "x": 0,
      "z": 10,
      "type": "normal"
    },
    {
      "x": 0,
      "z": 8,
      "type": "fragile"
    },
    {
      "x": 0,
      "z": 9,
      "type": "normal"
    },
    {
      "x": 0,
      "z": 7,
      "type": "normal"
    },
    {
      "x": -2,
      "z": 7,
      "type": "normal"
    },
    {
      "x": -1,
      "z": 7,
      "type": "fragile"
    },
    {
      "x": -2,
      "z": 6,
      "type": "normal"
    },
    {
      "x": -1,
      "z": 6,
      "type": "normal"
    },
    {
      "x": -2,
      "z": 5,
      "type": "fragile"
    },
    {
      "x": -1,
      "z": 5,
      "type": "fragile"
    },
    {
      "x": -2,
      "z": 4,
      "type": "normal"
    },
    {
      "x": -1,
      "z": 4,
      "type": "normal"
    },
    {
      "x": -2,
      "z": 3,
      "type": "normal"
    },
    {
      "x": -1,
      "z": 3,
      "type": "fragile"
    },
    {
      "x": 0,
      "z": 3,
      "type": "normal"
    },
    {
      "x": 0,
      "z": 1,
      "type": "normal"
    },
    {
      "x": 0,
      "z": 2,
      "type": "fragile"
    },
    {
      "x": 0,
      "z": 0,
      "type": "normal"
    }
  ],
  "solution_data": [
    "up",
    "up",
    "right",
    "up",
    "right",
    "right",
    "down",
    "down",
    "left",
    "up",
    "left",
    "down",
    "right",
    "up",
    "up",
    "right",
    "down",
    "down",
    "left",
    "left",
    "down",
    "right",
    "up",
    "up",
    "left",
    "up",
    "left",
    "up",
    "up",
    "right",
    "down",
    "right",
    "down",
    "down",
    "down",
    "right",
    "up",
    "right",
    "up",
    "up",
    "up",
    "up",
    "left",
    "up",
    "up",
    "up",
    "up",
    "right",
    "up",
    "up"
  ]
}