{
  "level_metadata": {
    "id": "lvl_46",
    "difficulty": 9,
    "seed": 553449893,
    "steps_to_solve": 29,
    "island_count": 2,
    "map_bounds": {
      "minX": 0,
      "maxX": 21,
      "minZ": -4,
      "maxZ": 4,
      "width": 22,
      "length": 9
    },
    "layout_dir": "20deg",
    "slot": 46,
    "phase": "abyss",
    "mechanics": {
      "fragile": true,
      "crumbling": true,
      "moving": true,
      "portal": true,
      "fragileRate": 0.35,
      "crumblingRate": 0.18,
      "constraintMode": true
    },
    "generator": {
      "base_seed": 773224723,
      "attempts": 9,
      "verified": true,
      "dir_angle_deg": 20,
      "spreadDeg": 120,
      "deviationPct": 0.3,
      "crossAxisLimit": 7
    },
    "tile_stats": {
      "normal": 23,
      "fragile": 17,
      "crumbling": 6,
      "moving": 1,
      "portal": 2,
      "total": 49,
      "trap_density": 0.49
    },
    "computed_difficulty": 8.62,
    "behavioral_analysis": {
      "precision_moves": 11,
      "crumbling_moves": 6,
      "orientation_changes": 22,
      "portal_traversals": 1,
      "critical_tile_count": 49,
      "critical_hazard_count": 24,
      "behavioral_difficulty": 8.62
    },
    "applied_patterns": [
      {
        "pattern": "FRAGILE_BRIDGE",
        "index": 12
      },
      {
        "pattern": "ONE_TIME_PATH",
        "index": 17
      }
    ]
  },
  "world_settings": {
    "environment": "abyss_default",
    "gravity": 1
  },
  "start_state": {
    "pos": {
      "x": 21,
      "z": 4
    },
    "orientation": "vertical"
  },
  "hole_pos": {
    "x": 0,
    "z": -1
  },
  "tiles": [
    {
      "x": 21,
      "z": 4,
      "type": "normal"
    },
    {
      "x": 19,
      "z": 4,
      "type": "fragile"
    },
    {
      "x": 20,
      "z": 4,
      "type": "normal"
    },
    {
      "x": 19,
      "z": 3,
      "type": "normal"
    },
    {
      "x": 20,
      "z": 3,
      "type": "crumbling"
    },
    {
      "x": 18,
      "z": 3,
      "type": "normal"
    },
    {
      "x": 18,
      "z": 1,
      "type": "normal"
    },
    {
      "x": 18,
      "z": 2,
      "type": "normal"
    },
    {
      "x": 17,
      "z": 1,
      "type": "fragile"
    },
    {
      "x": 17,
      "z": 2,
      "type": "fragile"
    },
    {
      "x": 17,
      "z": 0,
      "type": "normal"
    },
    {
      "x": 17,
      "z": -2,
      "type": "normal"
    },
    {
      "x": 17,
      "z": -1,
      "type": "normal"
    },
    {
      "x": 16,
      "z": -2,
      "type": "normal"
    },
    {
      "x": 16,
      "z": -1,
      "type": "normal"
    },
    {
      "x": 16,
      "z": -3,
      "type": "normal"
    },
    {
      "x": 14,
      "z": -3,
      "type": "fragile"
    },
    {
      "x": 15,
      "z": -3,
      "type": "normal"
    },
    {
      "x": 13,
      "z": -3,
      "type": "portal",
      "target": {
        "x": 5,
        "z": 2
      }
    },
    {
      "x": 5,
      "z": 2,
      "type": "portal",
      "target": {
        "x": 13,
        "z": -3
      }
    },
    {
      "x": 6,
      "z": 2,
      "type": "crumbling"
    },
    {
      "x": 7,
      "z": 2,
      "type": "normal"
    },
    {
      "x": 6,
      "z": 3,
      "type": "fragile"
    },
    {
      "x": 7,
      "z": 3,
      "type": "fragile"
    },
    {
      "x": 8,
      "z": 3,
      "type": "normal"
    },
    {
      "x": 8,
      "z": 1,
      "type": "fragile"
    },
    {
      "x": 8,
      "z": 2,
      "type": "fragile"
    },
    {
      "x": 8,
      "z": 0,
      "type": "moving",
      "params": {
        "axis": "x",
        "range": [
          7,
          9
        ],
        "stepsPerPhase": 2,
        "startPhase": 0
      }
    },
    {
      "x": 8,
      "z": -2,
      "type": "fragile"
    },
    {
      "x": 8,
      "z": -1,
      "type": "fragile"
    },
    {
      "x": 7,
      "z": -2,
      "type": "crumbling"
    },
    {
      "x": 7,
      "z": -1,
      "type": "fragile"
    },
    {
      "x": 7,
      "z": -3,
      "type": "crumbling"
    },
    {
      "x": 5,
      "z": -3,
      "type": "fragile"
    },
    {
      "x": 6,
      "z": -3,
      "type": "fragile"
    },
    {
      "x": 5,
      "z": -4,
      "type": "normal"
    },
    {
      "x": 6,
      "z": -4,
      "type": "fragile"
    },
    {
      "x": 4,
      "z": -4,
      "type": "normal"
    },
    {
      "x": 4,
      "z": -3,
      "type": "fragile"
    },
    {
      "x": 4,
      "z": -2,
      "type": "fragile"
    },
    {
      "x": 4,
      "z": -1,
      "type": "crumbling"
    },
    {
      "x": 2,
      "z": -1,
      "type": "normal"
    },
    {
      "x": 3,
      "z": -1,
      "type": "normal"
    },
    {
      "x": 3,
      "z": 0,
      "type": "normal"
    },
    {
      "x": 4,
      "z": 0,
      "type": "normal"
    },
    {
      "x": 4,
      "z": 1,
      "type": "fragile"
    },
    {
      "x": 3,
      "z": 1,
      "type": "normal"
    },
    {
      "x": 1,
      "z": -1,
      "type": "crumbling"
    },
    {
      "x": 0,
      "z": -1,
      "type": "normal"
    }
  ],
  "solution_data": [
    "left",
    "up",
    "left",
    "up",
    "left",
    "up",
    "up",
    "left",
    "up",
    "left",
    "left",
    "right",
    "down",
    "right",
    "up",
    "up",
    "up",
    "left",
    "up",
    "left",
    "up",
    "left",
    "down",
    "down",
    "down",
    "left",
    "up",
    "left",
    "left"
  ]
}