{
  "level_metadata": {
    "id": "lvl_47",
    "difficulty": 9,
    "seed": 2836322696,
    "steps_to_solve": 27,
    "island_count": 2,
    "map_bounds": {
      "minX": 0,
      "maxX": 21,
      "minZ": -4,
      "maxZ": 4,
      "width": 22,
      "length": 9
    },
    "layout_dir": "20deg",
    "slot": 47,
    "phase": "abyss",
    "mechanics": {
      "fragile": true,
      "crumbling": true,
      "moving": true,
      "portal": true,
      "fragileRate": 0.35,
      "crumblingRate": 0.18
    },
    "generator": {
      "base_seed": 4747,
      "attempts": 1,
      "verified": true,
      "dir_angle_deg": 20,
      "spreadDeg": 120,
      "deviationPct": 0.3,
      "crossAxisLimit": 7
    },
    "tile_stats": {
      "normal": 25,
      "fragile": 9,
      "crumbling": 10,
      "moving": 0,
      "portal": 2,
      "total": 46,
      "trap_density": 0.413
    },
    "computed_difficulty": 3.36
  },
  "world_settings": {
    "environment": "abyss_default",
    "gravity": 1
  },
  "start_state": {
    "pos": {
      "x": 10,
      "z": -3
    },
    "orientation": "vertical"
  },
  "hole_pos": {
    "x": 16,
    "z": -3
  },
  "tiles": [
    {
      "x": 10,
      "z": -3,
      "type": "normal"
    },
    {
      "x": 10,
      "z": -2,
      "type": "normal"
    },
    {
      "x": 10,
      "z": -1,
      "type": "normal"
    },
    {
      "x": 11,
      "z": -2,
      "type": "normal"
    },
    {
      "x": 11,
      "z": -1,
      "type": "crumbling"
    },
    {
      "x": 11,
      "z": 0,
      "type": "normal"
    },
    {
      "x": 11,
      "z": 1,
      "type": "fragile"
    },
    {
      "x": 11,
      "z": 2,
      "type": "fragile"
    },
    {
      "x": 11,
      "z": 3,
      "type": "normal"
    },
    {
      "x": 9,
      "z": 3,
      "type": "normal"
    },
    {
      "x": 10,
      "z": 3,
      "type": "normal"
    },
    {
      "x": 8,
      "z": 3,
      "type": "normal"
    },
    {
      "x": 6,
      "z": 3,
      "type": "crumbling"
    },
    {
      "x": 7,
      "z": 3,
      "type": "fragile"
    },
    {
      "x": 5,
      "z": 3,
      "type": "crumbling"
    },
    {
      "x": 5,
      "z": 1,
      "type": "normal"
    },
    {
      "x": 5,
      "z": 2,
      "type": "normal"
    },
    {
      "x": 5,
      "z": 0,
      "type": "normal"
    },
    {
      "x": 3,
      "z": 0,
      "type": "normal"
    },
    {
      "x": 4,
      "z": 0,
      "type": "normal"
    },
    {
      "x": 2,
      "z": 0,
      "type": "normal"
    },
    {
      "x": 2,
      "z": -2,
      "type": "fragile"
    },
    {
      "x": 2,
      "z": -1,
      "type": "fragile"
    },
    {
      "x": 3,
      "z": -2,
      "type": "normal"
    },
    {
      "x": 3,
      "z": -1,
      "type": "crumbling"
    },
    {
      "x": 3,
      "z": -3,
      "type": "normal"
    },
    {
      "x": 1,
      "z": -3,
      "type": "fragile"
    },
    {
      "x": 2,
      "z": -3,
      "type": "normal"
    },
    {
      "x": 0,
      "z": -3,
      "type": "portal",
      "target": {
        "x": 20,
        "z": -2
      }
    },
    {
      "x": 20,
      "z": -2,
      "type": "portal",
      "target": {
        "x": 0,
        "z": -3
      }
    },
    {
      "x": 20,
      "z": -1,
      "type": "crumbling"
    },
    {
      "x": 20,
      "z": 0,
      "type": "crumbling"
    },
    {
      "x": 19,
      "z": -1,
      "type": "normal"
    },
    {
      "x": 19,
      "z": 0,
      "type": "normal"
    },
    {
      "x": 18,
      "z": -1,
      "type": "normal"
    },
    {
      "x": 18,
      "z": 0,
      "type": "crumbling"
    },
    {
      "x": 17,
      "z": -1,
      "type": "fragile"
    },
    {
      "x": 17,
      "z": 0,
      "type": "normal"
    },
    {
      "x": 17,
      "z": 1,
      "type": "crumbling"
    },
    {
      "x": 18,
      "z": 1,
      "type": "fragile"
    },
    {
      "x": 19,
      "z": 1,
      "type": "normal"
    },
    {
      "x": 17,
      "z": -2,
      "type": "crumbling"
    },
    {
      "x": 18,
      "z": -2,
      "type": "fragile"
    },
    {
      "x": 17,
      "z": -3,
      "type": "normal"
    },
    {
      "x": 18,
      "z": -3,
      "type": "crumbling"
    },
    {
      "x": 16,
      "z": -3,
      "type": "normal"
    }
  ],
  "solution_data": [
    "down",
    "right",
    "down",
    "down",
    "down",
    "left",
    "left",
    "left",
    "left",
    "up",
    "up",
    "left",
    "left",
    "up",
    "right",
    "up",
    "left",
    "left",
    "down",
    "left",
    "down",
    "left",
    "up",
    "up",
    "up",
    "up",
    "left"
  ]
}